{
  "nom_du_produit": "Lot 6 Balles Anti-Stress Sensorielles",
  "slug": "balles-anti-stress-sensorielles",
  "category": "anti-stress",
  "brand": "Impresa",
  "introduction": "Lot 6 Balles Anti-Stress Sensorielles par Impresa. Contenu: 6 balles. Diamètre: 5-6 cm",
  "avantages": "<ul><li>6 textures différentes</li><li>< 15€</li><li>Silencieux</li><li>Durables</li></ul>",
  "inconvenients": "<ul><li>Odeur chimique initiale</li><li>Tailles non uniformes</li></ul>",
  "verdict": "Note: 4.4/5",
  "performances": "Contenu: 6 balles. Diamètre: 5-6 cm",
  "note": 8.8,
  "amazon_link_short": "https://www.amazon.fr/dp/B08B3GWH9D?tag=materielgamer-21",
  "seo_title": "Lot 6 Balles Anti-Stress Sensorielles - Test & Avis 2026",
  "meta_description": "Lot 6 Balles Anti-Stress Sensorielles: test complet, avis et comparatif."
}