{
  "nom_du_produit": "Bougie Soja Lavande 50h",
  "slug": "bougie-soja-lavande",
  "category": "aromatherapie",
  "brand": "La Jolie Muse",
  "introduction": "Bougie Soja Lavande 50h par La Jolie Muse. Combustion: ~50h. Poids: 400 g",
  "avantages": "<ul><li>Soja naturelle</li><li>HE lavande authentique</li><li>50h combustion</li><li>Mèche sans plomb</li></ul>",
  "inconvenients": "<ul><li>Parfum subtil</li><li>Ramollit en été</li></ul>",
  "verdict": "Note: 4.4/5",
  "performances": "Combustion: ~50h. Poids: 400 g",
  "note": 8.8,
  "amazon_link_short": "https://www.amazon.fr/dp/B07H79Y5TM?tag=materielgamer-21",
  "seo_title": "Bougie Soja Lavande 50h - Test & Avis 2026",
  "meta_description": "Bougie Soja Lavande 50h: test complet, avis et comparatif."
}