{
  "nom_du_produit": "Uni-ball Jetstream SXN-210",
  "slug": "uniball-jetstream-ergonomique",
  "category": "journaling-ecriture-therapeutique",
  "brand": "Uni-ball",
  "introduction": "Uni-ball Jetstream SXN-210 par Uni-ball. Pointe: 1.0 mm. Type: Hybride",
  "avantages": "<ul><li>Jetstream ultra-fluide</li><li>Grip ergonomique</li><li>Sans bavure</li><li>Gauchers OK</li><li>Recharges dispo</li></ul>",
  "inconvenients": "<ul><li>Recharges spécifiques</li><li>1 pointe</li></ul>",
  "verdict": "Note: 4.6/5",
  "performances": "Pointe: 1.0 mm. Type: Hybride",
  "note": 9.2,
  "amazon_link_short": "https://www.amazon.fr/dp/B002FSZP5A?tag=materielgamer-21",
  "seo_title": "Uni-ball Jetstream SXN-210 - Test & Avis 2026",
  "meta_description": "Uni-ball Jetstream SXN-210: test complet, avis et comparatif."
}